simpleflow/__init__.py
simpleflow/__main__.py
simpleflow/_decorators.py
simpleflow/activity.py
simpleflow/base.py
simpleflow/boto3_utils.py
simpleflow/canvas.py
simpleflow/command.py
simpleflow/constants.py
simpleflow/download.py
simpleflow/exceptions.py
simpleflow/execute.py
simpleflow/executor.py
simpleflow/format.py
simpleflow/futures.py
simpleflow/history.py
simpleflow/log.py
simpleflow/logging_context.py
simpleflow/marker.py
simpleflow/metrology.py
simpleflow/registry.py
simpleflow/signal.py
simpleflow/storage.py
simpleflow/task.py
simpleflow/workflow.py
simpleflow/dispatch/__init__.py
simpleflow/dispatch/by_module.py
simpleflow/dispatch/dry_run.py
simpleflow/dispatch/dynamic_dispatcher.py
simpleflow/dispatch/exceptions.py
simpleflow/dispatch/from_task_registry.py
simpleflow/job/__init__.py
simpleflow/local/__init__.py
simpleflow/local/executor.py
simpleflow/process/__init__.py
simpleflow/process/_named_mixin.py
simpleflow/process/_supervisor.py
simpleflow/runtime/__init__.py
simpleflow/settings/__init__.py
simpleflow/settings/base.py
simpleflow/settings/default.py
simpleflow/step/__init__.py
simpleflow/step/constants.py
simpleflow/step/submittable.py
simpleflow/step/tasks.py
simpleflow/step/utils.py
simpleflow/step/workflow.py
simpleflow/swf/__init__.py
simpleflow/swf/constants.py
simpleflow/swf/executor.py
simpleflow/swf/helpers.py
simpleflow/swf/task.py
simpleflow/swf/utils.py
simpleflow/swf/mapper/__init__.py
simpleflow/swf/mapper/constants.py
simpleflow/swf/mapper/core.py
simpleflow/swf/mapper/exceptions.py
simpleflow/swf/mapper/settings.py
simpleflow/swf/mapper/utils.py
simpleflow/swf/mapper/actors/__init__.py
simpleflow/swf/mapper/actors/core.py
simpleflow/swf/mapper/actors/decider.py
simpleflow/swf/mapper/actors/worker.py
simpleflow/swf/mapper/models/__init__.py
simpleflow/swf/mapper/models/activity.py
simpleflow/swf/mapper/models/base.py
simpleflow/swf/mapper/models/domain.py
simpleflow/swf/mapper/models/workflow.py
simpleflow-0.34.1.dist-info/METADATA
simpleflow-0.34.1.dist-info/WHEEL
simpleflow-0.34.1.dist-info/entry_points.txt
simpleflow-0.34.1.dist-info/licenses/LICENSE
simpleflow-0.34.1.dist-info/RECORD
