Metadata-Version: 2.4
Name: simpleflow
Version: 0.34.1
Summary: Python library for dataflow programming with Amazon SWF
Project-URL: documentation, https://botify-labs.github.io/simpleflow
Project-URL: repository, https://github.com/botify-labs/simpleflow
Project-URL: changelog, https://github.com/botify-labs/simpleflow/blob/main/CHANGELOG.md
Author: Greg Leclercq
Maintainer-email: tech@botify.com
License-Expression: MIT
License-File: LICENSE
Keywords: amazon swf,simple workflow,simpleflow
Classifier: Development Status :: 4 - Beta
Classifier: Intended Audience :: Developers
Classifier: License :: OSI Approved :: MIT License
Classifier: Natural Language :: English
Classifier: Programming Language :: Python :: 3
Classifier: Programming Language :: Python :: 3.7
Classifier: Programming Language :: Python :: 3.8
Classifier: Programming Language :: Python :: 3.9
Classifier: Programming Language :: Python :: 3.10
Classifier: Programming Language :: Python :: 3.11
Classifier: Programming Language :: Python :: 3.12
Classifier: Programming Language :: Python :: 3.13
Requires-Python: >=3.7
Requires-Dist: attrs
Requires-Dist: boto3>=1.28.20
Requires-Dist: click
Requires-Dist: dill>=0.3.6
Requires-Dist: diskcache>=4.1.0
Requires-Dist: jinja2
Requires-Dist: lazy-object-proxy
Requires-Dist: lockfile>=0.9.1
Requires-Dist: markupsafe
Requires-Dist: multiprocess>=0.70.14
Requires-Dist: psutil
Requires-Dist: pytz
Requires-Dist: setproctitle
Requires-Dist: tabulate<1.0.0,>=0.8.2
